ln_macro/__init__.py
ln_macro/macro.py
ln_macro/noop.py
ln_macro/noop.yml
LN_Macro-1.0.0.dist-info/AUTHORS.rst
LN_Macro-1.0.0.dist-info/LICENSE
LN_Macro-1.0.0.dist-info/METADATA
LN_Macro-1.0.0.dist-info/WHEEL
LN_Macro-1.0.0.dist-info/entry_points.txt
LN_Macro-1.0.0.dist-info/top_level.txt
LN_Macro-1.0.0.dist-info/zip-safe
LN_Macro-1.0.0.dist-info/RECORD
