Metadata-Version: 2.1
Name: LN-Macro
Version: 1.0.0
Summary: LiveNodes: node based live streaming sensor/data and visualization suite.
Author-email: Yale Hartmann <yale.hartmann@uni-bremen.de>
License: GNU GENERAL PUBLIC LICENSE
License-File: LICENSE
License-File: AUTHORS.rst
Requires-Dist: livenodes>=0.12.1b6
Requires-Dist: LN-Ports>=0.12.1b8
Requires-Dist: numpy>=1.24.4
Provides-Extra: dev
Requires-Dist: tox; extra == "dev"
Requires-Dist: pytest>=8.2.2; extra == "dev"
